[{
    "question" : "Laki-laki serius + Wanita serius = Menikah || Laki-laki serius + Wanita main-main = Tidak Menikah || Laki-laki main-main + Wanita Main-main = Pasti Cuma Buat Pacaran || JADI 1 + 4 Berapa?",
    "answer" : "CDEFIOUVWX41013141516"
}, {
    "question" : "Berapa sudut yang diperlukan untuk menikung pacar gebetan yang berdiri sejauh 100 meter bagi 50 ?",
    "answer" : "CDEFLRUVWX1713141516"
}, {
    "question" : "Ada Berapa tipe Method Class ?",
    "answer" : "CDEFLRUVWX41013141516"
}, {
    "question" : "Ada berapa stone di Film Avengers",
    "answer" : "CDEFIOVWX1471013141516"
}, {
    "question" : "Ada berapa super hero wanita di hacktiv8 MCC",
    "answer" : "CDEFLRUVWX1713141516"
}, {
    "question" : "Berapa panjang length dari S.H.I.E.L.D ?",
    "answer" : "CFILORUX147101316"
}, {
    "question" : "console.log ( passwordWifiMcc39.length );",
    "answer" : "ACDEFGILMORSUVWXY45101110141516"
}, {
    "question" : "How Many computers in Fase 1 class MCC?",
    "answer" : "GHIJKLORSTUVWXY45678910"
}, {
    "question" : "How Many Hacktiv8's Super Girl in MCC ?",
    "answer" : "ABCDEFLQV1611"
}]